hh_stats/__init__.py
hh_stats/__main__.py
hh_stats/cli.py
hh_stats/consts.py
hh_stats/hh_api.py
hh_stats/hh_api_ex.py
hh_stats/input_.py
hh_stats/logger.py
hh_stats/main.py
hh_stats/stats.py
hh_stats/utils.py
hh_stats/vacancy.py
hh_stats/output/__init__.py
hh_stats/output/csv.py
hh_stats/output/raw.py
hh_stats/output/svg.py
hh_stats-1.4.0.dist-info/DESCRIPTION.rst
hh_stats-1.4.0.dist-info/METADATA
hh_stats-1.4.0.dist-info/RECORD
hh_stats-1.4.0.dist-info/WHEEL
hh_stats-1.4.0.dist-info/entry_points.txt
hh_stats-1.4.0.dist-info/metadata.json
hh_stats-1.4.0.dist-info/top_level.txt
