Metadata-Version: 2.0
Name: hh-stats
Version: 1.4.0
Summary: Utility for a collection of a vacancies stats from hh.ru service
Home-page: https://github.com/thewizardplusplus/hh-stats
Author: thewizardplusplus
Author-email: thewizardplusplus@yandex.ru
License: MIT
Platform: UNKNOWN
Requires-Python: >=3.5, <4.0
Requires-Dist: jsonschema (<3.0,>=2.6.0)
Requires-Dist: matplotlib (<3.0,>=2.0.2)
Requires-Dist: parsedatetime (>=2.4,<3.0)
Requires-Dist: pytimeparse (>=1.1.6,<2.0)
Requires-Dist: requests (>=2.18.1,<3.0)
Requires-Dist: termcolor (<2.0,>=1.1.0)
Requires-Dist: tzlocal (<2.0,>=1.4)
